{
  "authority_statement": "Release decisions bind to the exact repo+commit identities below, derived exclusively from git rev-parse. The GitKB index is derived navigation state and is NEVER source or release authority.",
  "meta_coordination": "read-only evidence from /home/flexnetos/meta/.meta.yaml; no monorepo fusion; every peer remains an independent repository",
  "release_consumers": [
    "ARCHBP-021",
    "ARCHBP-025",
    "ARCHBP-047"
  ],
  "repos": [
    {
      "branch_current": true,
      "checked_out_branch": "codex/profile-xdg-owner-20260721",
      "head_commit": "38f8abaf5a8dd5638196d34afcf7762bbb1fb7d4",
      "identity_source": "git rev-parse (the KB index is derived state, never source authority)",
      "kb_default_branch": "master",
      "path": "/home/flexnetos/meta/src/envctl",
      "repo": "envctl"
    },
    {
      "branch_current": true,
      "checked_out_branch": "main",
      "head_commit": "da102a2110b4cf91cfc5ae31cdb90922c71174d2",
      "identity_source": "git rev-parse (the KB index is derived state, never source authority)",
      "kb_default_branch": "main",
      "path": "/home/flexnetos/meta/src/lifeos",
      "repo": "lifeos"
    },
    {
      "branch_current": true,
      "checked_out_branch": "main",
      "head_commit": "afbdc5d22f376c428dd6eff36c5ceefac22750d2",
      "identity_source": "git rev-parse (the KB index is derived state, never source authority)",
      "kb_default_branch": "main",
      "path": "/home/flexnetos/meta/src/meta-ruvector",
      "repo": "meta-ruvector"
    },
    {
      "branch_current": true,
      "checked_out_branch": "develop",
      "head_commit": "712591b6d7d23b50ba728cbd79834923b5e0340f",
      "identity_source": "git rev-parse (the KB index is derived state, never source authority)",
      "kb_default_branch": "master",
      "path": "/home/flexnetos/meta/src/nu_plugin",
      "repo": "nu_plugin"
    },
    {
      "branch_current": true,
      "checked_out_branch": "feat/rtk-full-feature-config",
      "head_commit": "04f9e2843224276404feb2f2fc8b249a328fade3",
      "identity_source": "git rev-parse (the KB index is derived state, never source authority)",
      "kb_default_branch": "develop",
      "path": "/home/flexnetos/meta/src/rtk-tokenkill",
      "repo": "rtk-tokenkill"
    },
    {
      "branch_current": true,
      "checked_out_branch": "main",
      "head_commit": "1bda2dc81edfde0cf525093660736f4750d8661e",
      "identity_source": "git rev-parse (the KB index is derived state, never source authority)",
      "kb_default_branch": "main",
      "path": "/home/flexnetos/meta/src/vault_hub",
      "repo": "vault_hub"
    },
    {
      "branch_current": true,
      "checked_out_branch": "codex/profile-xdg-owner-20260721",
      "head_commit": "83d4ac8b7debb71afbe2bbda07e7a0257aa23380",
      "identity_source": "git rev-parse (the KB index is derived state, never source authority)",
      "kb_default_branch": "main",
      "path": "/home/flexnetos/meta/src/yazelix",
      "repo": "yazelix"
    }
  ],
  "schema_version": "lifeos.release-isolation-map.v0"
}
