{
  "schema_version": "lifeos-planning-spine.proof-record.v0",
  "task_id": "PRESERVE-001",
  "observed_at": "2026-07-10T23:37:00Z",
  "revision": 1,
  "status": "pass",
  "verification_gate": "All relocation inputs were archived and checksum-verified before mutation.",
  "gate_result": {
    "archive_root": "/home/flexnetos/.local/state/meta/archives/20260710T224253Z-meta-authority-relocation",
    "sha256_manifest": "ab12117a8d7c3124befaa40126825dcd4f3028579e63bf21fa90920b716cec35",
    "checksum_verification_passed": true,
    "unarchived_destructive_actions": 0
  }
}
