{
  "appended_entries": [
    {
      "generated_at": "2026-07-12T23:30:18Z",
      "observed_at": "2026-07-12T23:24:17Z",
      "proof_sha256": "d642857ea0d775273035122d5ce82415c8559407bc4759a824fb7d6bea9136fe",
      "proof_uri": "proof_records/ADOPT-001.proof.json",
      "revision": "1",
      "schema_version": "lifeos-planning-spine.proof-ledger.v0",
      "sequence": 161,
      "status": "pass",
      "task_id": "ADOPT-001"
    },
    {
      "generated_at": "2026-07-12T23:30:18Z",
      "observed_at": "2026-07-12T23:24:17Z",
      "proof_sha256": "09fecfdc3026164e285b656342da0e1e471767cc4671e07891d0205839d2a6b7",
      "proof_uri": "proof_records/ADOPT-002.proof.json",
      "revision": "1",
      "schema_version": "lifeos-planning-spine.proof-ledger.v0",
      "sequence": 162,
      "status": "pass",
      "task_id": "ADOPT-002"
    },
    {
      "generated_at": "2026-07-12T23:30:18Z",
      "observed_at": "2026-07-12T23:24:17Z",
      "proof_sha256": "91196fd795dc5d54411f8bde0811396ab89362453c93c38b9c8c5b810f04bda7",
      "proof_uri": "proof_records/GRAPH-002.proof.json",
      "revision": "1",
      "schema_version": "lifeos-planning-spine.proof-ledger.v0",
      "sequence": 163,
      "status": "pass",
      "task_id": "GRAPH-002"
    },
    {
      "generated_at": "2026-07-12T23:30:18Z",
      "observed_at": "2026-07-12T23:24:17Z",
      "proof_sha256": "293b99fe2c6126e8e269a4ba9dd73eed3cd2483055e054ac13378c7d3b1f3103",
      "proof_uri": "proof_records/GRAPH-003.proof.json",
      "revision": "1",
      "schema_version": "lifeos-planning-spine.proof-ledger.v0",
      "sequence": 164,
      "status": "pass",
      "task_id": "GRAPH-003"
    },
    {
      "generated_at": "2026-07-12T23:30:18Z",
      "observed_at": "2026-07-12T23:24:17Z",
      "proof_sha256": "a81cd05040380490261c9cd1778477dc4727a2561c55b7d1b41077ec273f6c18",
      "proof_uri": "proof_records/GRAPH-004.proof.json",
      "revision": "1",
      "schema_version": "lifeos-planning-spine.proof-ledger.v0",
      "sequence": 165,
      "status": "pass",
      "task_id": "GRAPH-004"
    }
  ],
  "appended_entry_count": 5,
  "dry_run": false,
  "existing_entry_count": 160,
  "final_entry_count": 165,
  "generated_at": "2026-07-12T23:30:18Z",
  "input_proof_count": 131,
  "ledger_path": "proof_records/proof_ledger.jsonl",
  "proof_dir": "proof_records",
  "result": "pass",
  "schema_version": "lifeos-planning-spine.proof-ledger.merge-report.v0",
  "skipped_entries": [
    {
      "path": "proof_records/CAP-001.proof.json",
      "revision": "4",
      "task_id": "CAP-001"
    },
    {
      "path": "proof_records/IDD-UNIFY-000.proof.json",
      "revision": "1",
      "task_id": "IDD-UNIFY-000"
    },
    {
      "path": "proof_records/IDD-UNIFY-001.proof.json",
      "revision": "1",
      "task_id": "IDD-UNIFY-001"
    },
    {
      "path": "proof_records/IDD-UNIFY-002.proof.json",
      "revision": "1",
      "task_id": "IDD-UNIFY-002"
    },
    {
      "path": "proof_records/LPS-000.proof.json",
      "revision": "3",
      "task_id": "LPS-000"
    },
    {
      "path": "proof_records/LPS-001.proof.json",
      "revision": "3",
      "task_id": "LPS-001"
    },
    {
      "path": "proof_records/LPS-002.proof.json",
      "revision": "3",
      "task_id": "LPS-002"
    },
    {
      "path": "proof_records/LPS-003.proof.json",
      "revision": "3",
      "task_id": "LPS-003"
    },
    {
      "path": "proof_records/LPS-004.proof.json",
      "revision": "3",
      "task_id": "LPS-004"
    },
    {
      "path": "proof_records/LPS-005.proof.json",
      "revision": "3",
      "task_id": "LPS-005"
    },
    {
      "path": "proof_records/LPS-006.proof.json",
      "revision": "3",
      "task_id": "LPS-006"
    },
    {
      "path": "proof_records/LPS-007.proof.json",
      "revision": "3",
      "task_id": "LPS-007"
    },
    {
      "path": "proof_records/LPS-008.proof.json",
      "revision": "3",
      "task_id": "LPS-008"
    },
    {
      "path": "proof_records/LPS-009.proof.json",
      "revision": "3",
      "task_id": "LPS-009"
    },
    {
      "path": "proof_records/LPS-010.proof.json",
      "revision": "3",
      "task_id": "LPS-010"
    },
    {
      "path": "proof_records/LPS-011.proof.json",
      "revision": "3",
      "task_id": "LPS-011"
    },
    {
      "path": "proof_records/LPS-012.proof.json",
      "revision": "2026-07-03T19:30:12Z",
      "task_id": "LPS-012"
    },
    {
      "path": "proof_records/LPS-013.proof.json",
      "revision": "2026-07-03T19:37:51Z",
      "task_id": "LPS-013"
    },
    {
      "path": "proof_records/LPS-014.proof.json",
      "revision": "2026-07-03T19:39:08Z",
      "task_id": "LPS-014"
    },
    {
      "path": "proof_records/LPS-015.proof.json",
      "revision": "2026-07-03T19:42:46Z",
      "task_id": "LPS-015"
    },
    {
      "path": "proof_records/LPS-016.proof.json",
      "revision": "2",
      "task_id": "LPS-016"
    },
    {
      "path": "proof_records/LPS-017.proof.json",
      "revision": "2",
      "task_id": "LPS-017"
    },
    {
      "path": "proof_records/LPS-018.proof.json",
      "revision": "4",
      "task_id": "LPS-018"
    },
    {
      "path": "proof_records/LPS-019.proof.json",
      "revision": "2026-07-03T18:30:22Z",
      "task_id": "LPS-019"
    },
    {
      "path": "proof_records/LPS-020.proof.json",
      "revision": "2026-07-03T18:42:37Z",
      "task_id": "LPS-020"
    },
    {
      "path": "proof_records/LPS-021.proof.json",
      "revision": "2026-07-03T18:46:59Z",
      "task_id": "LPS-021"
    },
    {
      "path": "proof_records/LPS-022.proof.json",
      "revision": "2026-07-03T18:50:10Z",
      "task_id": "LPS-022"
    },
    {
      "path": "proof_records/LPS-023.proof.json",
      "revision": "1",
      "task_id": "LPS-023"
    },
    {
      "path": "proof_records/LPS-024.proof.json",
      "revision": "1",
      "task_id": "LPS-024"
    },
    {
      "path": "proof_records/LPS-025.proof.json",
      "revision": "1",
      "task_id": "LPS-025"
    },
    {
      "path": "proof_records/LPS-026.proof.json",
      "revision": "1",
      "task_id": "LPS-026"
    },
    {
      "path": "proof_records/LPS-027.proof.json",
      "revision": "1",
      "task_id": "LPS-027"
    },
    {
      "path": "proof_records/LPS-028.proof.json",
      "revision": "1",
      "task_id": "LPS-028"
    },
    {
      "path": "proof_records/LPS-030.proof.json",
      "revision": "1",
      "task_id": "LPS-030"
    },
    {
      "path": "proof_records/NBSOURCE-000.proof.json",
      "revision": "1",
      "task_id": "NBSOURCE-000"
    },
    {
      "path": "proof_records/NBSOURCE-001.proof.json",
      "revision": "1",
      "task_id": "NBSOURCE-001"
    },
    {
      "path": "proof_records/NBSOURCE-002.proof.json",
      "revision": "1",
      "task_id": "NBSOURCE-002"
    },
    {
      "path": "proof_records/NBSOURCE-003.proof.json",
      "revision": "1",
      "task_id": "NBSOURCE-003"
    },
    {
      "path": "proof_records/NBSOURCE-004.proof.json",
      "revision": "2",
      "task_id": "NBSOURCE-004"
    },
    {
      "path": "proof_records/NBSOURCE-005.proof.json",
      "revision": "1",
      "task_id": "NBSOURCE-005"
    },
    {
      "path": "proof_records/NBSOURCE-007.proof.json",
      "revision": "1",
      "task_id": "NBSOURCE-007"
    },
    {
      "path": "proof_records/NBSOURCE-008.proof.json",
      "revision": "1",
      "task_id": "NBSOURCE-008"
    },
    {
      "path": "proof_records/NBSOURCE-009.proof.json",
      "revision": "1",
      "task_id": "NBSOURCE-009"
    },
    {
      "path": "proof_records/NBSOURCE-010.proof.json",
      "revision": "1",
      "task_id": "NBSOURCE-010"
    },
    {
      "path": "proof_records/NBSOURCE-011.proof.json",
      "revision": "1",
      "task_id": "NBSOURCE-011"
    },
    {
      "path": "proof_records/NBSOURCE-012.proof.json",
      "revision": "1",
      "task_id": "NBSOURCE-012"
    },
    {
      "path": "proof_records/NBSOURCE-013.proof.json",
      "revision": "1",
      "task_id": "NBSOURCE-013"
    },
    {
      "path": "proof_records/NBSOURCE-014.proof.json",
      "revision": "1",
      "task_id": "NBSOURCE-014"
    },
    {
      "path": "proof_records/NBSOURCE-015.proof.json",
      "revision": "1",
      "task_id": "NBSOURCE-015"
    },
    {
      "path": "proof_records/NBSOURCE-016.proof.json",
      "revision": "1",
      "task_id": "NBSOURCE-016"
    },
    {
      "path": "proof_records/NBSOURCE-017.proof.json",
      "revision": "1",
      "task_id": "NBSOURCE-017"
    },
    {
      "path": "proof_records/NBSOURCE-018.proof.json",
      "revision": "1",
      "task_id": "NBSOURCE-018"
    },
    {
      "path": "proof_records/NBSOURCE-019.proof.json",
      "revision": "1",
      "task_id": "NBSOURCE-019"
    },
    {
      "path": "proof_records/NBSOURCE-020.proof.json",
      "revision": "1",
      "task_id": "NBSOURCE-020"
    },
    {
      "path": "proof_records/NBSOURCE-021.proof.json",
      "revision": "1",
      "task_id": "NBSOURCE-021"
    },
    {
      "path": "proof_records/NBSOURCE-022.proof.json",
      "revision": "1",
      "task_id": "NBSOURCE-022"
    },
    {
      "path": "proof_records/NBSOURCE-023.proof.json",
      "revision": "1",
      "task_id": "NBSOURCE-023"
    },
    {
      "path": "proof_records/NBSOURCE-024.proof.json",
      "revision": "1",
      "task_id": "NBSOURCE-024"
    },
    {
      "path": "proof_records/NBSOURCE-025.proof.json",
      "revision": "1",
      "task_id": "NBSOURCE-025"
    },
    {
      "path": "proof_records/NBSOURCE-026.proof.json",
      "revision": "1",
      "task_id": "NBSOURCE-026"
    },
    {
      "path": "proof_records/NBSOURCE-027.proof.json",
      "revision": "1",
      "task_id": "NBSOURCE-027"
    },
    {
      "path": "proof_records/NBSOURCE-028.proof.json",
      "revision": "1",
      "task_id": "NBSOURCE-028"
    },
    {
      "path": "proof_records/NBSOURCE-029.proof.json",
      "revision": "1",
      "task_id": "NBSOURCE-029"
    },
    {
      "path": "proof_records/NBSOURCE-030.proof.json",
      "revision": "1",
      "task_id": "NBSOURCE-030"
    },
    {
      "path": "proof_records/NBSOURCE-031.proof.json",
      "revision": "1",
      "task_id": "NBSOURCE-031"
    },
    {
      "path": "proof_records/NBSOURCE-032.proof.json",
      "revision": "1",
      "task_id": "NBSOURCE-032"
    },
    {
      "path": "proof_records/NBSTATED-001.proof.json",
      "revision": "1",
      "task_id": "NBSTATED-001"
    },
    {
      "path": "proof_records/NBSTATED-002.proof.json",
      "revision": "1",
      "task_id": "NBSTATED-002"
    },
    {
      "path": "proof_records/NBSTATED-003.proof.json",
      "revision": "1",
      "task_id": "NBSTATED-003"
    },
    {
      "path": "proof_records/NBSTATED-004.proof.json",
      "revision": "1",
      "task_id": "NBSTATED-004"
    },
    {
      "path": "proof_records/NBSTATED-005.proof.json",
      "revision": "1",
      "task_id": "NBSTATED-005"
    },
    {
      "path": "proof_records/NBSTATED-006.proof.json",
      "revision": "1",
      "task_id": "NBSTATED-006"
    },
    {
      "path": "proof_records/NBSTATED-007.proof.json",
      "revision": "1",
      "task_id": "NBSTATED-007"
    },
    {
      "path": "proof_records/NBSTATED-008.proof.json",
      "revision": "1",
      "task_id": "NBSTATED-008"
    },
    {
      "path": "proof_records/NBSTATED-009.proof.json",
      "revision": "1",
      "task_id": "NBSTATED-009"
    },
    {
      "path": "proof_records/NBSTATED-010.proof.json",
      "revision": "1",
      "task_id": "NBSTATED-010"
    },
    {
      "path": "proof_records/NBSTATED-011.proof.json",
      "revision": "1",
      "task_id": "NBSTATED-011"
    },
    {
      "path": "proof_records/NBSTATED-012.proof.json",
      "revision": "1",
      "task_id": "NBSTATED-012"
    },
    {
      "path": "proof_records/NBSTATED-013.proof.json",
      "revision": "1",
      "task_id": "NBSTATED-013"
    },
    {
      "path": "proof_records/NBSTATED-014.proof.json",
      "revision": "1",
      "task_id": "NBSTATED-014"
    },
    {
      "path": "proof_records/NBSTATED-015.proof.json",
      "revision": "1",
      "task_id": "NBSTATED-015"
    },
    {
      "path": "proof_records/NBSTATED-016.proof.json",
      "revision": "1",
      "task_id": "NBSTATED-016"
    },
    {
      "path": "proof_records/NBSTATED-017.proof.json",
      "revision": "1",
      "task_id": "NBSTATED-017"
    },
    {
      "path": "proof_records/NBSTATED-018.proof.json",
      "revision": "1",
      "task_id": "NBSTATED-018"
    },
    {
      "path": "proof_records/NBSTATED-019.proof.json",
      "revision": "1",
      "task_id": "NBSTATED-019"
    },
    {
      "path": "proof_records/NBSTATED-020.proof.json",
      "revision": "1",
      "task_id": "NBSTATED-020"
    },
    {
      "path": "proof_records/NBSTATED-021.proof.json",
      "revision": "1",
      "task_id": "NBSTATED-021"
    },
    {
      "path": "proof_records/NBSTATED-022.proof.json",
      "revision": "1",
      "task_id": "NBSTATED-022"
    },
    {
      "path": "proof_records/NBSTATED-023.proof.json",
      "revision": "1",
      "task_id": "NBSTATED-023"
    },
    {
      "path": "proof_records/NBSTATED-024.proof.json",
      "revision": "1",
      "task_id": "NBSTATED-024"
    },
    {
      "path": "proof_records/NBSTATED-025.proof.json",
      "revision": "1",
      "task_id": "NBSTATED-025"
    },
    {
      "path": "proof_records/NBSTATED-026.proof.json",
      "revision": "1",
      "task_id": "NBSTATED-026"
    },
    {
      "path": "proof_records/NBSTATED-027.proof.json",
      "revision": "1",
      "task_id": "NBSTATED-027"
    },
    {
      "path": "proof_records/NBSTATED-028.proof.json",
      "revision": "1",
      "task_id": "NBSTATED-028"
    },
    {
      "path": "proof_records/NBSTATED-029.proof.json",
      "revision": "1",
      "task_id": "NBSTATED-029"
    },
    {
      "path": "proof_records/NBSTATED-030.proof.json",
      "revision": "1",
      "task_id": "NBSTATED-030"
    },
    {
      "path": "proof_records/NBSTATED-031.proof.json",
      "revision": "1",
      "task_id": "NBSTATED-031"
    },
    {
      "path": "proof_records/NBSTATED-032.proof.json",
      "revision": "1",
      "task_id": "NBSTATED-032"
    },
    {
      "path": "proof_records/NBVERIFY-000.proof.json",
      "revision": "1",
      "task_id": "NBVERIFY-000"
    },
    {
      "path": "proof_records/NBVERIFY-001.proof.json",
      "revision": "1",
      "task_id": "NBVERIFY-001"
    },
    {
      "path": "proof_records/NBVERIFY-001-v2.proof.json",
      "revision": "2",
      "task_id": "NBVERIFY-001"
    },
    {
      "path": "proof_records/NBVERIFY-002.proof.json",
      "revision": "1",
      "task_id": "NBVERIFY-002"
    },
    {
      "path": "proof_records/NBVERIFY-002-v2.proof.json",
      "revision": "2",
      "task_id": "NBVERIFY-002"
    },
    {
      "path": "proof_records/NBVERIFY-003.proof.json",
      "revision": "1",
      "task_id": "NBVERIFY-003"
    },
    {
      "path": "proof_records/NBVERIFY-003-v2.proof.json",
      "revision": "2",
      "task_id": "NBVERIFY-003"
    },
    {
      "path": "proof_records/NBVERIFY-004.proof.json",
      "revision": "1",
      "task_id": "NBVERIFY-004"
    },
    {
      "path": "proof_records/NBVERIFY-004-v2.proof.json",
      "revision": "2",
      "task_id": "NBVERIFY-004"
    },
    {
      "path": "proof_records/NBVERIFY-030-032.proof.json",
      "revision": "1",
      "task_id": "NBVERIFY-030"
    },
    {
      "path": "proof_records/NORTHSTAR-001.proof.json",
      "revision": "1",
      "task_id": "NORTHSTAR-001"
    },
    {
      "path": "proof_records/NORTHSTAR-002.proof.json",
      "revision": "1",
      "task_id": "NORTHSTAR-002"
    },
    {
      "path": "proof_records/OPS-001.proof.json",
      "revision": "2",
      "task_id": "OPS-001"
    },
    {
      "path": "proof_records/PRESERVE-001.proof.json",
      "revision": "1",
      "task_id": "PRESERVE-001"
    },
    {
      "path": "proof_records/PRESERVE-002.proof.json",
      "revision": "1",
      "task_id": "PRESERVE-002"
    },
    {
      "path": "proof_records/PRESERVE-003.proof.json",
      "revision": "2",
      "task_id": "PRESERVE-003"
    },
    {
      "path": "proof_records/RECOVERY-001.proof.json",
      "revision": "1",
      "task_id": "RECOVERY-001"
    },
    {
      "path": "proof_records/RECOVERY-002.proof.json",
      "revision": "1",
      "task_id": "RECOVERY-002"
    },
    {
      "path": "proof_records/RECOVERY-003.proof.json",
      "revision": "1",
      "task_id": "RECOVERY-003"
    },
    {
      "path": "proof_records/RECOVERY-004.proof.json",
      "revision": "2",
      "task_id": "RECOVERY-004"
    },
    {
      "path": "proof_records/STRUCTURE-001.proof.json",
      "revision": "1",
      "task_id": "STRUCTURE-001"
    },
    {
      "path": "proof_records/STRUCTURE-002.proof.json",
      "revision": "1",
      "task_id": "STRUCTURE-002"
    },
    {
      "path": "proof_records/STRUCTURE-003.proof.json",
      "revision": "1",
      "task_id": "STRUCTURE-003"
    },
    {
      "path": "proof_records/STRUCTURE-004.proof.json",
      "revision": "1",
      "task_id": "STRUCTURE-004"
    },
    {
      "path": "proof_records/STRUCTURE-005.proof.json",
      "revision": "1",
      "task_id": "STRUCTURE-005"
    },
    {
      "path": "proof_records/STRUCTURE-006.proof.json",
      "revision": "1",
      "task_id": "STRUCTURE-006"
    },
    {
      "path": "proof_records/STRUCTURE-006-v2.proof.json",
      "revision": "2",
      "task_id": "STRUCTURE-006"
    },
    {
      "path": "proof_records/WEAVE-001.proof.json",
      "revision": "2",
      "task_id": "WEAVE-001"
    }
  ],
  "skipped_entry_count": 126
}
