{
  "bundle_path": "planning-spine-v0/examples/mvp-bundle.json",
  "observed_at": "2026-07-20T21:51:44.427Z",
  "result": "fail",
  "message": "planning-spine-v0 MVP bundle verification failed: Agent navigation graph drifted: navigation/generated/navigation_graph.json is stale; navigation/generated/navigation_index.json is stale; navigation/generated/navigation.validation_report.json is stale",
  "bundle_id": null,
  "scope": null,
  "scope_boundaries": null,
  "bundle_order": [],
  "resolved_objects": {},
  "authority_assignment": null,
  "linkage_checks": []
}
